{"cameraMode":{"drawMode":0,"name":"Shaded","section":"Shading Mode"},"sceneLighting":true,"audioPlay":false,"sceneViewState":{"showFog":true,"showMaterialUpdate":false,"showSkybox":true,"showFlares":true,"showImageEffects":true,"showParticleSystems":true},"in2DMode":false,"pivot":{"x":11.414288520812989,"y":-31.01476287841797,"z":51.18046569824219},"rotation":{"x":0.43216463923454287,"y":0.24427145719528199,"z":-0.12270857393741608,"w":0.859427273273468},"size":36.15488052368164,"orthographic":false}